reversefold/__init__.py
reversefold/util/__init__.py
reversefold/util/daemonize.py
reversefold/util/follow.py
reversefold/util/log.py
reversefold/util/multiproc.py
reversefold/util/mysqlping.py
reversefold/util/proc.py
reversefold/util/proc2.py
reversefold/util/sort_json.py
reversefold/util/ssh.py
reversefold/util/stream.py
reversefold/util/tail.py
reversefold.util-3.5.5.dist-info/entry_points.txt
reversefold.util-3.5.5.dist-info/WHEEL
reversefold.util-3.5.5.dist-info/METADATA
reversefold.util-3.5.5.dist-info/RECORD
