Metadata-Version: 2.1
Name: reversefold.util
Version: 3.5.5
Summary: SSH, Proc, Multiproc, tail.py, log.py, stream.py, daemonize.py, etc.
Home-page: https://github.com/reversefold/util
License: MIT
Author: Justin Patrin
Author-email: papercrane@reversefold.com
Requires-Python: >3.4,<4
Classifier: License :: OSI Approved :: MIT License
Classifier: Programming Language :: Python :: 3
Classifier: Programming Language :: Python :: 3.5
Classifier: Programming Language :: Python :: 3.6
Classifier: Programming Language :: Python :: 3.7
Classifier: Programming Language :: Python :: 3.8
Classifier: Programming Language :: Python :: 3.9
Requires-Dist: colorama (>=0.4.1,<0.5.0)
Requires-Dist: docopt (>=0.6.2,<0.7.0)
Requires-Dist: fasteners (>=0.15.0,<0.16.0)
Requires-Dist: psutil (>=5.6,<6.0)
Requires-Dist: python-daemon (>=2.1,<3.0)
Requires-Dist: watchdog (>=0.9.0,<0.10.0)
Project-URL: Repository, https://github.com/reversefold/util.git
